easyTCP2/__init__.py
easyTCP2/__main__.py
easyTCP2/Client/Client.py
easyTCP2/Client/__init__.py
easyTCP2/Core/Decorators.py
easyTCP2/Core/Protocol.py
easyTCP2/Core/Settings.py
easyTCP2/Core/__init__.py
easyTCP2/Exceptions/ClientExceptions.py
easyTCP2/Exceptions/GroupExceptions.py
easyTCP2/Exceptions/ServerClientExceptions.py
easyTCP2/Exceptions/__init__.py
easyTCP2/Server/Client.py
easyTCP2/Server/Groups.py
easyTCP2/Server/Server.py
easyTCP2/Server/__init__.py
easyTCP2/Utils/Build_in.py
easyTCP2/Utils/__init__.py
easyTCP2/Utils/functions.py
easyTCP2-0.1.0.dist-info/LICENSE
easyTCP2-0.1.0.dist-info/METADATA
easyTCP2-0.1.0.dist-info/WHEEL
easyTCP2-0.1.0.dist-info/top_level.txt
easyTCP2-0.1.0.dist-info/RECORD
