Metadata-Version: 2.1
Name: easyTCP2
Version: 0.1.0
Summary: rich async server and easy to config
Home-page: https://github.com/dsal3389/easyTCP2
Author: Daniel Sonbolian
Author-email: dsal3389@gmail.com
License: MIT
Download-URL: https://github.com/dsal3389/easyTCP2.git
Platform: UNKNOWN
Classifier: Intended Audience :: Developers
Classifier: License :: OSI Approved :: MIT License
Classifier: Programming Language :: Python :: 3.7
Requires-Python: >=3.7
